hdrconv/__init__.py
hdrconv/convert/__init__.py
hdrconv/convert/apple.py
hdrconv/convert/colorspace.py
hdrconv/convert/gainmap.py
hdrconv/convert/transfer.py
hdrconv/core/__init__.py
hdrconv/core/types.py
hdrconv/identify/__init__.py
hdrconv/identify/apple_heic.py
hdrconv/io/__init__.py
hdrconv/io/apple_heic.py
hdrconv/io/ios_hdr_screenshot.py
hdrconv/io/iso21496.py
hdrconv/io/iso22028.py
hdrconv/io/ultrahdr.py
hdr_conversion-0.1.2.dist-info/METADATA
hdr_conversion-0.1.2.dist-info/WHEEL
hdr_conversion-0.1.2.dist-info/licenses/LICENSE
hdr_conversion-0.1.2.dist-info/RECORD
