Metadata-Version: 2.4
Name: hdr-conversion
Version: 0.1.2
Summary: tools for converting HDR images between different formats
License-File: LICENSE
Requires-Python: >=3.11
Requires-Dist: colour-science>=0.4.6
Requires-Dist: imagecodecs>=2025.11.11
Requires-Dist: pillow-heif>=0.22.0
Requires-Dist: pillow>=11.3.0
Requires-Dist: pyexiftool>=0.5.6
